draughtsman/__init__.py
draughtsman/__main__.py
draughtsman/drafter.py
draughtsman-0.2.0.dist-info/LICENSE
draughtsman-0.2.0.dist-info/METADATA
draughtsman-0.2.0.dist-info/WHEEL
draughtsman-0.2.0.dist-info/top_level.txt
draughtsman-0.2.0.dist-info/RECORD
