Metadata-Version: 2.1
Name: draughtsman
Version: 0.2.0
Summary: API Blueprint Parser for Python
Home-page: https://github.com/kylef/draughtsman
Author: Kyle Fuller
Author-email: kyle@fuller.li
License: BSD
Platform: UNKNOWN
Classifier: Development Status :: 5 - Production/Stable
Classifier: Programming Language :: Python :: 3.5
Classifier: Programming Language :: Python :: 3.6
Classifier: Programming Language :: Python :: 3.7
Classifier: Programming Language :: Python :: 3.8
Classifier: License :: OSI Approved :: BSD License
Requires-Dist: cffi
Requires-Dist: refract (==0.4.0)
Requires-Dist: semantic-version
